mirrorclock/api.py
mirrorclock/bi.py
mirrorclock/cli.py
mirrorclock/standalone.py
mirrorclock/wsgi.py
mirrorclock_gczuczy-0.4.dist-info/LICENSE
mirrorclock_gczuczy-0.4.dist-info/METADATA
mirrorclock_gczuczy-0.4.dist-info/WHEEL
mirrorclock_gczuczy-0.4.dist-info/entry_points.txt
mirrorclock_gczuczy-0.4.dist-info/top_level.txt
mirrorclock_gczuczy-0.4.dist-info/RECORD
