Metadata-Version: 2.1
Name: mirrorclock-gczuczy
Version: 0.4
Summary: Mirroclock example
Home-page: https://github.com/gczuczy/mirrorclock
Author: Gergely Czuczy
Author-email: gergely.czuczy@harmless.hu
Project-URL: Bug Tracker, https://github.com/gczuczy/mirrorclock/issues
Classifier: Programming Language :: Python :: 3
Classifier: License :: OSI Approved :: BSD License
Classifier: Operating System :: OS Independent
Classifier: Intended Audience :: Developers
Requires-Python: >=3.8
License-File: LICENSE
Requires-Dist: Flask (>=2.1.2)
Requires-Dist: Flask-RESTful (>=0.3.9)
